{
    "user_id": "ebf2f4e4-b4b9-4b47-9339-ccdb391de013",
    "name": "Sammy Hessel",
    "email": "Myriam_Wisozk-Gorczany64@gmail.com",
    "instagram_handle": "@Cheyanne_Denesik61",
    "tiktok_handle": "@Linwood_Lind-OConner51",
    "joined_at": "2024-04-11T15:18:43.359Z",
    "advocacy_programs": [
        {
            "program_id": "e5a72ce0-9cbd-4f70-9530-cb271e0b20b5",
            "brand": "Beahan - Powlowski",
            "tasks_completed": [
                {
                    "task_id": "096b4a08-4dc0-4492-ba28-5cbf900a3500",
                    "platform": "TikTok",
                    "post_url": "https://sick-pendant.info",
                    "likes": 48,
                    "comments": 8,
                    "shares": 35,
                    "reach": 7936
                }
            ],
            "total_sales_attributed": 4601.318927194066
        }
    ]
}