{
    "user_id": null,
    "name": "???",
    "email": "invalid-email",
    "instagram_handle": null,
    "tiktok_handle": "#error_handle",
    "joined_at": "not-a-date",
    "advocacy_programs": [
        {
            "program_id": "",
            "brand": 12345,
            "tasks_completed": [
                {
                    "task_id": "10e1fbde-6730-45ed-8c07-3ee43eb07035",
                    "platform": "Facebook",
                    "post_url": "https://classic-scaffold.name",
                    "likes": "NaN",
                    "comments": null,
                    "shares": 70,
                    "reach": 6482
                }
            ],
            "total_sales_attributed": "no-data"
        }
    ]
}