{
    "user_id": null,
    "name": "???",
    "email": "invalid-email",
    "instagram_handle": "@Justice.Senger82",
    "tiktok_handle": "#error_handle",
    "joined_at": "not-a-date",
    "advocacy_programs": [
        {
            "program_id": "77556c65-3a5d-4f48-b23b-3cfe3e87db09",
            "brand": 12345,
            "tasks_completed": [
                {
                    "task_id": null,
                    "platform": "Instagram",
                    "post_url": "broken_link",
                    "likes": "NaN",
                    "comments": null,
                    "shares": 3,
                    "reach": 1470
                }
            ],
            "total_sales_attributed": "no-data"
        }
    ]
}