{
    "user_id": "4dbb7641-678c-4f5e-8eb4-17bea813aa4b",
    "name": "Margie Greenholt",
    "email": "Danny27@gmail.com",
    "instagram_handle": "@Myrtie11",
    "tiktok_handle": "@Bertha.Predovic58",
    "joined_at": "2024-11-16T09:16:10.381Z",
    "advocacy_programs": [
        {
            "program_id": "44c94b13-3b80-47f9-9afe-9c685db4a9b7",
            "brand": "Glover Inc",
            "tasks_completed": [
                {
                    "task_id": "740e175b-9842-4f15-867b-d65f5c9dd5d6",
                    "platform": "Instagram",
                    "post_url": "https://putrid-bog.biz/",
                    "likes": 399,
                    "comments": 18,
                    "shares": 57,
                    "reach": 9212
                }
            ],
            "total_sales_attributed": 326.64950797718154
        }
    ]
}