{
    "user_id": "ad466bca-7e4b-403e-8153-8bd8451f0357",
    "name": "Delbert Barton",
    "email": "Ollie.Langworth-Halvorson@hotmail.com",
    "instagram_handle": "@Hudson29",
    "tiktok_handle": "@Mac_Hartmann",
    "joined_at": "2024-03-26T02:49:13.239Z",
    "advocacy_programs": [
        {
            "program_id": "48cff13b-6d72-4e17-a19e-0652e3477d43",
            "brand": "Stanton Group",
            "tasks_completed": [
                {
                    "task_id": "fbabce09-1536-43df-94c5-5252128a5c67",
                    "platform": "TikTok",
                    "post_url": "https://french-negotiation.com/",
                    "likes": 437,
                    "comments": 30,
                    "shares": 34,
                    "reach": 643
                }
            ],
            "total_sales_attributed": 4901.883207712693
        }
    ]
}