{
    "user_id": "382664f4-0b76-4d80-ae55-73b64f524e8d",
    "name": "Toby Bashirian",
    "email": "Brenden_McClure28@yahoo.com",
    "instagram_handle": "@Providenci.Haag",
    "tiktok_handle": "@Deron_Koelpin",
    "joined_at": "2024-08-10T04:00:54.092Z",
    "advocacy_programs": [
        {
            "program_id": "5b485c6a-b58d-411c-9c3b-af20f8eb3864",
            "brand": "Rodriguez - Ward",
            "tasks_completed": [
                {
                    "task_id": "d43a8211-51ac-4ee2-ab46-f225a6b8bd19",
                    "platform": "Instagram",
                    "post_url": "https://actual-summer.biz/",
                    "likes": 174,
                    "comments": 46,
                    "shares": 11,
                    "reach": 8585
                }
            ],
            "total_sales_attributed": 812.0500905798813
        }
    ]
}