{
    "user_id": "ff55261c-2599-4b63-a1db-842d9b616b30",
    "name": "Latoya Abshire-Mosciski IV",
    "email": "Ernest_Mraz-Gleason87@yahoo.com",
    "instagram_handle": "@Alysson32",
    "tiktok_handle": "@Eliezer.Pfannerstill",
    "joined_at": "2024-07-20T20:01:26.712Z",
    "advocacy_programs": [
        {
            "program_id": "01198ad1-ad42-48c5-9436-fa84b96eb7c0",
            "brand": "Dicki Group",
            "tasks_completed": [
                {
                    "task_id": "399af2e6-fbc3-4159-be0d-685ab0c203ed",
                    "platform": "Instagram",
                    "post_url": "https://ornate-cutover.net/",
                    "likes": 497,
                    "comments": 28,
                    "shares": 49,
                    "reach": 4568
                }
            ],
            "total_sales_attributed": 1711.1754655062055
        }
    ]
}