{
    "user_id": "b613072d-0198-4418-81b0-b3856c1c0d14",
    "name": "Constance Altenwerth",
    "email": "Karina_Stiedemann52@gmail.com",
    "instagram_handle": "@Josie.Schinner37",
    "tiktok_handle": "@Dedrick.Block",
    "joined_at": "2024-12-14T20:02:41.752Z",
    "advocacy_programs": [
        {
            "program_id": "a4be033a-8201-4582-9c64-cb18f54b80e2",
            "brand": "Schultz Inc",
            "tasks_completed": [
                {
                    "task_id": "a2c4032f-dc8e-4cd8-bbc1-801c0fc7954c",
                    "platform": "TikTok",
                    "post_url": "https://cute-rim.name",
                    "likes": 463,
                    "comments": 12,
                    "shares": 52,
                    "reach": 2952
                }
            ],
            "total_sales_attributed": 3085.394881990895
        }
    ]
}