{
    "user_id": "5199891c-c7f1-470a-ba96-17086b3635ac",
    "name": "Don Witting",
    "email": "Alex.Hudson@yahoo.com",
    "instagram_handle": "@Addison10",
    "tiktok_handle": "@Brown.Schoen",
    "joined_at": "2024-11-25T16:13:32.757Z",
    "advocacy_programs": [
        {
            "program_id": "ab5e37f9-62fd-44af-80dc-9ac03ab1fc97",
            "brand": "Kutch Group",
            "tasks_completed": [
                {
                    "task_id": "0334d408-c28f-424e-9897-503d312d614c",
                    "platform": "Instagram",
                    "post_url": "https://distinct-individual.com/",
                    "likes": 144,
                    "comments": 11,
                    "shares": 90,
                    "reach": 6366
                }
            ],
            "total_sales_attributed": 934.4153476728542
        }
    ]
}