{
    "user_id": "673a438b-7778-4df8-815f-5ae39cafb0b3",
    "name": "Essie Schiller",
    "email": "Francisca_Wunsch10@yahoo.com",
    "instagram_handle": "@Nathanial_Padberg",
    "tiktok_handle": "@Alec26",
    "joined_at": "2024-04-25T21:55:02.957Z",
    "advocacy_programs": [
        {
            "program_id": "b489ef9c-04ed-4622-87a3-12b2f804d4f7",
            "brand": "Vandervort, Mayer and Grady",
            "tasks_completed": [
                {
                    "task_id": "f5c43860-5573-418e-adc1-54d44936b429",
                    "platform": "TikTok",
                    "post_url": "https://meaty-custody.biz/",
                    "likes": 96,
                    "comments": 33,
                    "shares": 74,
                    "reach": 2979
                }
            ],
            "total_sales_attributed": 2837.745003304696
        }
    ]
}