{
    "user_id": "bd5ad4db-adcb-40fb-a2c2-e18da71b309d",
    "name": "May Klein DDS",
    "email": "Aaron37@hotmail.com",
    "instagram_handle": "@Shaylee_Brekke",
    "tiktok_handle": "@Adelia.Sawayn",
    "joined_at": "2024-03-26T12:45:18.118Z",
    "advocacy_programs": [
        {
            "program_id": "a9f57ee9-8826-47aa-afd5-674b70c890eb",
            "brand": "Stehr LLC",
            "tasks_completed": [
                {
                    "task_id": "4ab7e915-cfec-4d16-b401-d1fbad3de3d2",
                    "platform": "Instagram",
                    "post_url": "https://enraged-morbidity.info",
                    "likes": 173,
                    "comments": 44,
                    "shares": 54,
                    "reach": 2967
                }
            ],
            "total_sales_attributed": 3647.6620073474405
        }
    ]
}