{
    "user_id": "4e6ad355-10f5-4d0c-bf3d-956e53310757",
    "name": "Helen Renner",
    "email": "Mike64@gmail.com",
    "instagram_handle": "@Lori.Hand24",
    "tiktok_handle": "@Waldo9",
    "joined_at": "2024-11-15T21:54:09.166Z",
    "advocacy_programs": [
        {
            "program_id": "e392da2c-e821-451c-bab1-502dd02e8350",
            "brand": "Oberbrunner, Donnelly and Kuphal",
            "tasks_completed": [
                {
                    "task_id": "9b115beb-e441-497b-815d-36debe53ce96",
                    "platform": "TikTok",
                    "post_url": "https://boiling-seagull.info",
                    "likes": 243,
                    "comments": 16,
                    "shares": 29,
                    "reach": 7280
                }
            ],
            "total_sales_attributed": 4248.89865007983
        }
    ]
}