{
    "user_id": "f08f9ed7-c900-4c1a-8712-535a2f5949ef",
    "name": "Mary Denesik",
    "email": "Humberto57@gmail.com",
    "instagram_handle": "@Ricky.Predovic45",
    "tiktok_handle": "@Ernest2",
    "joined_at": "2024-12-15T06:13:20.125Z",
    "advocacy_programs": [
        {
            "program_id": "0a2e0c64-2183-4b74-bfd1-199c84a0b5d5",
            "brand": "Gislason Inc",
            "tasks_completed": [
                {
                    "task_id": "c4a8f2b2-3965-4d39-81bb-5af4c0a1e3c4",
                    "platform": "Instagram",
                    "post_url": "https://outlandish-begonia.com/",
                    "likes": 174,
                    "comments": 26,
                    "shares": 24,
                    "reach": 7652
                }
            ],
            "total_sales_attributed": 1009.0501703552865
        }
    ]
}