{
    "user_id": "46dd1aea-84a8-4329-9cd4-760aed6a89b0",
    "name": "Sylvester Buckridge",
    "email": "Mariam_Sawayn@hotmail.com",
    "instagram_handle": "@Bette.Altenwerth",
    "tiktok_handle": "@Chasity.Zboncak78",
    "joined_at": "2024-12-21T02:01:07.561Z",
    "advocacy_programs": [
        {
            "program_id": "a6fabf57-0e0a-4c8e-bfda-0d72cfdc321c",
            "brand": "Corwin - Dicki",
            "tasks_completed": [
                {
                    "task_id": "8f3fe6a3-a136-4a1e-be3a-b0e709c5b64a",
                    "platform": "Instagram",
                    "post_url": "https://huge-tentacle.info/",
                    "likes": 240,
                    "comments": 27,
                    "shares": 13,
                    "reach": 3899
                }
            ],
            "total_sales_attributed": 2340.871920553972
        }
    ]
}