{
    "user_id": "67381156-5d8d-40f1-a95e-441a6a0feb35",
    "name": "Bonnie Morissette DDS",
    "email": "Makenna10@yahoo.com",
    "instagram_handle": "@Rozella4",
    "tiktok_handle": "@Barbara_Cole13",
    "joined_at": "2024-11-05T21:27:59.086Z",
    "advocacy_programs": [
        {
            "program_id": "15bdf5c5-a668-413e-8a92-4f79a30b4f82",
            "brand": "Schmitt - Hegmann",
            "tasks_completed": [
                {
                    "task_id": "b42e4e09-8f75-4c28-b477-7b832169681c",
                    "platform": "TikTok",
                    "post_url": "https://aggressive-translation.net/",
                    "likes": 65,
                    "comments": 8,
                    "shares": 46,
                    "reach": 5871
                }
            ],
            "total_sales_attributed": 261.16953873757996
        }
    ]
}