{
    "user_id": "c5e42532-db91-4c8d-95b0-a386ef622054",
    "name": "Michelle Ankunding",
    "email": "Alyce_Macejkovic@yahoo.com",
    "instagram_handle": "@Grover3",
    "tiktok_handle": "@Oswald.Pagac30",
    "joined_at": "2025-01-22T10:54:06.974Z",
    "advocacy_programs": [
        {
            "program_id": "9d838cf5-0f01-453c-b586-e61c707860b2",
            "brand": "Moore, Predovic and Hartmann",
            "tasks_completed": [
                {
                    "task_id": "edc761f1-d2b8-4547-9e33-a0051fb5c994",
                    "platform": "Instagram",
                    "post_url": "https://annual-provider.name/",
                    "likes": 358,
                    "comments": 13,
                    "shares": 89,
                    "reach": 8240
                }
            ],
            "total_sales_attributed": 2693.120292510005
        }
    ]
}