{
    "user_id": "c272f1fb-62fa-478e-8961-1388d5661fb3",
    "name": "Mark Mohr",
    "email": "Caden83@hotmail.com",
    "instagram_handle": "@Marisa_Mertz",
    "tiktok_handle": "@Cleora52",
    "joined_at": "2024-07-26T05:10:41.670Z",
    "advocacy_programs": [
        {
            "program_id": "970f79ec-2599-407a-b4e8-1d8984d22ff0",
            "brand": "Monahan Group",
            "tasks_completed": [
                {
                    "task_id": "ece1b271-d716-4d62-8e72-6ec562e5c959",
                    "platform": "TikTok",
                    "post_url": "https://key-birdbath.net",
                    "likes": 365,
                    "comments": 10,
                    "shares": 45,
                    "reach": 8879
                }
            ],
            "total_sales_attributed": 1999.1221567002433
        }
    ]
}