{
    "user_id": "7b3d95ce-def1-4b93-9b1f-e22bd9de470b",
    "name": "Dr. Tasha Hand",
    "email": "Hulda.Block@gmail.com",
    "instagram_handle": "@Patsy23",
    "tiktok_handle": "@Dustin30",
    "joined_at": "2024-06-20T14:44:56.158Z",
    "advocacy_programs": [
        {
            "program_id": "f29cc22a-6680-4c2d-aa1f-d61ac8b2507a",
            "brand": "Weimann Inc",
            "tasks_completed": [
                {
                    "task_id": "4e15a371-0d8a-4127-853f-ff18709366ca",
                    "platform": "Instagram",
                    "post_url": "https://closed-disconnection.net/",
                    "likes": 345,
                    "comments": 2,
                    "shares": 37,
                    "reach": 3741
                }
            ],
            "total_sales_attributed": 4143.16322654792
        }
    ]
}