{
    "user_id": "582d74f9-d9c4-4ded-b038-519183d8c91f",
    "name": "Dwayne Lesch",
    "email": "Reina.Rogahn36@yahoo.com",
    "instagram_handle": "@Geovanny.Koch",
    "tiktok_handle": "@Amari25",
    "joined_at": "2024-08-27T13:50:40.144Z",
    "advocacy_programs": [
        {
            "program_id": "b786b0ca-ad9a-4d92-8e1d-150af79e11a6",
            "brand": "Halvorson and Sons",
            "tasks_completed": [
                {
                    "task_id": "f9c14681-729e-4356-b79f-1472e3914523",
                    "platform": "TikTok",
                    "post_url": "https://prime-developmental.biz",
                    "likes": 127,
                    "comments": 12,
                    "shares": 0,
                    "reach": 6126
                }
            ],
            "total_sales_attributed": 2185.706447284958
        }
    ]
}