{
    "user_id": "e06f0e1c-08f8-4a0c-ad03-c45f4b1e00b9",
    "name": "Mrs. Patricia Conn-Lindgren",
    "email": "Lindsey4@gmail.com",
    "instagram_handle": "@Isai.Fadel62",
    "tiktok_handle": "@Annalise_Lakin46",
    "joined_at": "2024-04-01T14:42:22.330Z",
    "advocacy_programs": [
        {
            "program_id": "6250a9d6-c57d-414e-97ee-b0f5cf8bc72a",
            "brand": "Cormier LLC",
            "tasks_completed": [
                {
                    "task_id": "6d105cc9-a7e5-48f5-975d-3493cc0c1b99",
                    "platform": "Instagram",
                    "post_url": "https://musty-perfection.name",
                    "likes": 409,
                    "comments": 21,
                    "shares": 38,
                    "reach": 719
                }
            ],
            "total_sales_attributed": 4476.58409085965
        }
    ]
}