{
    "user_id": "35b8b1fe-daba-45d0-adf5-b9d20e8fa55f",
    "name": "Suzanne Volkman",
    "email": "Elton.Swaniawski@yahoo.com",
    "instagram_handle": "@Timmy.Oberbrunner90",
    "tiktok_handle": "@Natasha43",
    "joined_at": "2024-06-05T12:32:14.856Z",
    "advocacy_programs": [
        {
            "program_id": "7a7ea829-fe21-49ce-a070-d592239e1239",
            "brand": "Kovacek - Johns",
            "tasks_completed": [
                {
                    "task_id": "c33de83e-7626-4493-84a7-11223f32e6f4",
                    "platform": "Instagram",
                    "post_url": "https://jagged-fisherman.biz",
                    "likes": 103,
                    "comments": 5,
                    "shares": 86,
                    "reach": 2871
                }
            ],
            "total_sales_attributed": 4175.854259698564
        }
    ]
}