{
    "user_id": "78fb176e-340f-4692-bf80-c680c4ae7184",
    "name": "Chad Wuckert",
    "email": "Hazle15@yahoo.com",
    "instagram_handle": "@Taylor1",
    "tiktok_handle": "@Leon_Towne70",
    "joined_at": "2025-02-13T22:44:57.244Z",
    "advocacy_programs": [
        {
            "program_id": "19222d2a-6583-489d-9593-b2e485e8bb86",
            "brand": "Johns, Waters and Mueller",
            "tasks_completed": [
                {
                    "task_id": "1f71dcdf-a873-4d9b-ad82-23605ab372a8",
                    "platform": "TikTok",
                    "post_url": "https://gentle-ethyl.net",
                    "likes": 498,
                    "comments": 25,
                    "shares": 52,
                    "reach": 9905
                }
            ],
            "total_sales_attributed": 4535.804705436642
        }
    ]
}