{
    "user_id": "cf7a4a20-38ba-461d-80a8-b264da16f55c",
    "name": "Gilbert Macejkovic",
    "email": "Coy90@gmail.com",
    "instagram_handle": "@Mertie_Dare21",
    "tiktok_handle": "@Hilda.Bailey52",
    "joined_at": "2025-03-01T14:17:31.174Z",
    "advocacy_programs": [
        {
            "program_id": "9ba0ace5-ab47-4fd4-97ff-b71ecfe5edec",
            "brand": "Kutch - Gislason",
            "tasks_completed": [
                {
                    "task_id": "a7fd07aa-3f51-4e2d-bb0c-bc43fa5999e8",
                    "platform": "Instagram",
                    "post_url": "https://unlucky-polarisation.name/",
                    "likes": 372,
                    "comments": 15,
                    "shares": 73,
                    "reach": 5412
                }
            ],
            "total_sales_attributed": 3498.468696855921
        }
    ]
}