{
    "user_id": "f2746469-68d2-4d8b-ba99-06e4f7d1c47b",
    "name": "Jeffery Rau IV",
    "email": "Jammie.Heathcote@hotmail.com",
    "instagram_handle": "@Clifton.Green",
    "tiktok_handle": "@Kris43",
    "joined_at": "2025-02-16T10:21:08.220Z",
    "advocacy_programs": [
        {
            "program_id": "ce4ff7cd-389f-46d3-8eb2-5e7e5b5b8a43",
            "brand": "Paucek Inc",
            "tasks_completed": [
                {
                    "task_id": "f0e9ac72-0bac-44ac-a0b0-09b9f881bbf1",
                    "platform": "TikTok",
                    "post_url": "https://dull-lieu.com",
                    "likes": 136,
                    "comments": 47,
                    "shares": 9,
                    "reach": 6584
                }
            ],
            "total_sales_attributed": 4594.319853425158
        }
    ]
}