{
    "user_id": "078b8731-d85f-49aa-990d-95da93446eb8",
    "name": "Angie Weber",
    "email": "Lucious.Vandervort@hotmail.com",
    "instagram_handle": "@Deontae.Reichel31",
    "tiktok_handle": "@Nash44",
    "joined_at": "2024-10-10T22:57:15.972Z",
    "advocacy_programs": [
        {
            "program_id": "5464b042-4997-49df-b4ce-1543b0698db4",
            "brand": "Watsica, Stracke and Schulist",
            "tasks_completed": [
                {
                    "task_id": "ace3c517-0733-415c-a7f4-48ef85422e1e",
                    "platform": "TikTok",
                    "post_url": "https://lazy-cd.org/",
                    "likes": 481,
                    "comments": 44,
                    "shares": 57,
                    "reach": 4791
                }
            ],
            "total_sales_attributed": 3797.138053849033
        }
    ]
}