{
    "user_id": "b2c6b6ba-c238-44c3-b29e-8253bb742420",
    "name": "Wilfred Tromp",
    "email": "Titus_Becker25@hotmail.com",
    "instagram_handle": "@Beaulah.OHara48",
    "tiktok_handle": "@Erick_Shanahan",
    "joined_at": "2024-06-24T13:21:56.823Z",
    "advocacy_programs": [
        {
            "program_id": "6f3034ca-9ea1-4ef9-8a09-2f90f85bd6e3",
            "brand": "Koss Inc",
            "tasks_completed": [
                {
                    "task_id": "ab1bac6e-3380-40cb-b9fa-97d4e63eee34",
                    "platform": "Instagram",
                    "post_url": "https://esteemed-underneath.biz/",
                    "likes": 345,
                    "comments": 1,
                    "shares": 66,
                    "reach": 8670
                }
            ],
            "total_sales_attributed": 3924.9411456539947
        }
    ]
}