{
    "user_id": "17207e9d-a0c5-4a58-9751-beb627135ac1",
    "name": "Maxine Armstrong",
    "email": "Emilia_Kub@hotmail.com",
    "instagram_handle": "@Lia85",
    "tiktok_handle": "@Zelda79",
    "joined_at": "2024-05-01T11:46:22.920Z",
    "advocacy_programs": [
        {
            "program_id": "b475f7d5-4c0a-4041-a7a4-214b8c8e0016",
            "brand": "Collins, Oberbrunner and Donnelly",
            "tasks_completed": [
                {
                    "task_id": "8fecade3-be7e-4b78-b9fc-f3b1a6780184",
                    "platform": "TikTok",
                    "post_url": "https://rural-completion.com/",
                    "likes": 339,
                    "comments": 37,
                    "shares": 36,
                    "reach": 774
                }
            ],
            "total_sales_attributed": 4203.355189580003
        }
    ]
}